srctools-2.6.1.dist-info/RECORD
srctools-2.6.1.dist-info/WHEEL
srctools-2.6.1.dist-info/entry_points.txt
srctools-2.6.1.dist-info/METADATA
srctools/surfaceprop.py
srctools/filesys.py
srctools/vec.py
srctools/vtf.py
srctools/run.py
srctools/_points_map.py
srctools/_py_vtf_readwrite.py
srctools/sndscript.py
srctools/fgd.lzma
srctools/game.py
srctools/_fgd_helpers.py
srctools/fgd.py
srctools/dmx.py
srctools/instancing.py
srctools/bsp.py
srctools/_cy_vtf_readwrite.pypy310-pp73-darwin.so
srctools/cmdseq.py
srctools/_shaderdb.py
srctools/__init__.py
srctools/_math.pypy310-pp73-darwin.so
srctools/_engine_db.py
srctools/types.py
srctools/logger.py
srctools/particles.py
srctools/smd.py
srctools/tokenizer.py
srctools/vpk.py
srctools/keyvalues.py
srctools/binformat.py
srctools/mdl.py
srctools/geometry.py
srctools/_tokenizer.pypy310-pp73-darwin.so
srctools/_class_resources.py
srctools/vmt.py
srctools/py.typed
srctools/math.py
srctools/property_parser.py
srctools/packlist.py
srctools/steam.py
srctools/choreo.py
srctools/const.py
srctools/vmf.py
srctools/_pyinstaller/__init__.py
srctools/_pyinstaller/hook-srctools.py
srctools/scripts/__init__.py
srctools/scripts/build_scenes_image.py
srctools/scripts/collapse_manifest.py
srctools/scripts/make_model_folders.py
srctools/scripts/dump_parms.py
srctools/scripts/find_deps.py
srctools/scripts/diff.py
srctools/scripts/dump_proxies.py
