Metadata-Version: 2.1
Name: srctools
Version: 2.6.1
Summary: Modules for working with Valve's Source Engine file formats.
Keywords: Valve,Source Engine
Author-Email: TeamSpen210 <spencerb21@live.com>
License: MIT
Classifier: Development Status :: 5 - Production/Stable
Classifier: Framework :: Pytest
Classifier: Framework :: tox
Classifier: License :: OSI Approved :: MIT License
Classifier: Programming Language :: Cython
Classifier: Programming Language :: Python :: 3.9
Classifier: Programming Language :: Python :: 3.10
Classifier: Programming Language :: Python :: 3.11
Classifier: Programming Language :: Python :: 3.12
Classifier: Programming Language :: Python :: 3.13
Classifier: Programming Language :: Python :: 3 :: Only
Classifier: Programming Language :: Python :: Implementation :: CPython
Classifier: Programming Language :: Python :: Implementation :: PyPy
Classifier: Topic :: Games/Entertainment
Classifier: Topic :: Multimedia :: Graphics :: 3D Modeling
Classifier: Topic :: Scientific/Engineering :: Mathematics
Project-URL: source, https://github.com/TeamSpen210/srctools
Requires-Python: >=3.9
Requires-Dist: attrs>=22.2.0
Requires-Dist: typing_extensions>=4.12.0
Requires-Dist: exceptiongroup>=1.2.0; python_version < "3.11"
Requires-Dist: useful_types>=0.1.0
